Parity Checker/paritychecker.v
module parity_checker(x,clk,z);
input clk,x;
output reg z;
reg odd_even;
parameter Odd = 1, Even = 0;

always@(posedge clk)
 case(odd_even)
  Odd: odd_even = x?Even:Odd;
  Even : odd_even = x?Odd:Even;
  default: odd_even = Even;
 endcase

always@(odd_even)
 case(odd_even)
  Odd : z = 1;
  Even : z = 0;
  default: z =0;
 endcase
endmodule

Parity Checker/paritychecker_tb.v
module testp;
reg clk,x;
wire z;

parity_checker dut(.clk(clk), .x(x), .z(z) );

initial 
 begin 
  clk = 1'b0;
  repeat(2) begin
  #2 x =1; #10 x = 0; #10 x = 1; #10 x = 1; end
 end

always #5 clk = ~clk;

initial 
 begin
  $dumpfile("parity.vcd");
  $dumpvars(0,testp);
  #100 $finish;
  end
endmodule

Parity Checker/parity.vcd
$date
	Wed Nov 12 16:03:38 2025
$end
$version
	Icarus Verilog
$end
$timescale
	1s
$end
$scope module testp $end
$var wire 1 ! z $end
$var reg 1 " clk $end
$var reg 1 # x $end
$scope module dut $end
$var wire 1 " clk $end
$var wire 1 # x $end
$var parameter 32 $ Even $end
$var parameter 32 % Odd $end
$var reg 1 & odd_even $end
$var reg 1 ! z $end
$upscope $end
$upscope $end
$enddefinitions $end
$comment Show the parameter values. $end
$dumpall
b1 %
b0 $
$end
#0
$dumpvars
x&
x#
0"
x!
$end
#2
1#
#5
0!
0&
1"
#10
0"
#12
0#
#15
1"
#20
0"
#22
1#
#25
1!
1&
1"
#30
0"
#35
0!
0&
1"
#40
0"
#44
0#
#45
1"
#50
0"
#54
1#
#55
1!
1&
1"
#60
0"
#65
0!
0&
1"
#70
0"
#75
1!
1&
1"
#80
0"
#85
0!
0&
1"
#90
0"
#95
1!
1&
1"
